{
  "objectInfo" : {
    "id" : "594SCKdUTCTkni8tgk1t4Y",
    "name" : "P_Customer_details",
    "type" : "PROCESS",
    "metadata" : {
      "modelVersion" : {
        "major" : 1,
        "minor" : 0
      },
      "repoInfo" : {
        "repoHandle" : "TVMTonQYWeIssjq-gt-4213346-2026-02-17T13:41:19.726Z::pd.xml"
      },
      "contextAttributes" : null,
      "additionalInfo" : {
        "description" : "",
        "contentType" : "application/json; charset=utf-8",
        "documentState" : "VALID"
      }
    }
  },
  "dataFileExtension" : "xml",
  "updateTime" : "2026-04-23T09:55:14.523Z",
  "objectRefs" : [ {
    "id" : "9EJ4NQKy7gEhYN7OdTD6ac",
    "name" : "App-Thomas-Bayer",
    "type" : "AI_CONNECTION",
    "metadata" : {
      "modelVersion" : {
        "major" : 1,
        "minor" : 0
      },
      "repoInfo" : {
        "repoHandle" : "03puoJ49ARJi4tc-gt-4211282-2026-02-17T13:38:59.984Z::conn.xml"
      },
      "contextAttributes" : null,
      "additionalInfo" : {
        "description" : "",
        "contentType" : "application/json; charset=utf-8",
        "documentState" : "VALID"
      }
    },
    "path" : "/Explore/Ganesh_Motamarri/API"
  } ],
  "readableFileExtension" : null,
  "readableFilePresent" : false
}